ShootColor/__init__.py
ShootColor/colors.py
ShootColors-1.0.0.dist-info/LICENSE
ShootColors-1.0.0.dist-info/METADATA
ShootColors-1.0.0.dist-info/WHEEL
ShootColors-1.0.0.dist-info/top_level.txt
ShootColors-1.0.0.dist-info/RECORD
